inputwhile/__init__.py
inputwhile/modulo.py
inputwhile/utils.py
inputwhile-1.0.2.dist-info/LICENSE
inputwhile-1.0.2.dist-info/METADATA
inputwhile-1.0.2.dist-info/WHEEL
inputwhile-1.0.2.dist-info/top_level.txt
inputwhile-1.0.2.dist-info/RECORD
