Metadata-Version: 2.1
Name: inputwhile
Version: 1.0.2
Summary: A simple input while loop utility
Author: Benjas333
License-File: LICENSE
